Metadata-Version: 1.1
Name: mackerel.clienthde
Version: 0.0.4
Summary: Mackerel client implemented by Python.
Home-page: https://github.com/HDE/py-mackerel-client
Author: Shinya Ohyanagi, Iskandar Setiadi
Author-email: iskandarsetiadi@gmail.com
License: BSD
Platform: any
Classifier: Development Status :: 4 - Beta
Classifier: Environment :: Web Environment
Classifier: Intended Audience :: Developers
Classifier: License :: OSI Approved :: BSD License
Classifier: Operating System :: OS Independent
Classifier: Programming Language :: Python
